requirements.txt
setup.py
requests_etag_cache/__init__.py
requests_etag_cache.egg-info/PKG-INFO
requests_etag_cache.egg-info/SOURCES.txt
requests_etag_cache.egg-info/dependency_links.txt
requests_etag_cache.egg-info/top_level.txt