Metadata-Version: 2.1
Name: requests-etag-cache
Version: 2020.7.1
Summary: requests etag cache
Home-page: https://github.com/andrewp-as-is/requests-etag-cache.py
License: Unlicense
Keywords: requests cache
Platform: UNKNOWN
Classifier: License :: Public Domain
Classifier: Operating System :: OS Independent
Classifier: Programming Language :: Python :: 3
